pyclient2d/__init__.py
pyclient2d/Client/Client.py
pyclient2d/Client/__init__.py
pyclient2d/Math/__init__.py
pyclient2d/Math/_time.py
pyclient2d/Math/_typing.py
pyclient2d/Math/vector.py
pyclient2d/Server/Server.py
pyclient2d/Server/__init__.py
pyclient2d/Shared/Engine.py
pyclient2d/Shared/__init__.py
pyclient2d-0.0.3.dist-info/LICENSE
pyclient2d-0.0.3.dist-info/METADATA
pyclient2d-0.0.3.dist-info/WHEEL
pyclient2d-0.0.3.dist-info/top_level.txt
pyclient2d-0.0.3.dist-info/RECORD
